tracklr/__init__.py
tracklr/__main__.py
tracklr/add.py
tracklr/group.py
tracklr/info.py
tracklr/init.py
tracklr/ls.py
tracklr/main.py
tracklr/pdf.py
tracklr/vdir.py
tracklr-1.7.0.dist-info/licenses/LICENSE
tracklr_rest_api/__init__.py
tracklr_rest_api/serializers.py
tracklr_rest_api/views.py
tracklr-1.7.0.dist-info/METADATA
tracklr-1.7.0.dist-info/WHEEL
tracklr-1.7.0.dist-info/entry_points.txt
tracklr-1.7.0.dist-info/top_level.txt
tracklr-1.7.0.dist-info/RECORD
