Metadata-Version: 2.4
Name: tracklr
Version: 1.7.0
Summary: Tracklr - Command-line Productivity Toolset
Author-email: Marek Kuziel <marek@kuziel.info>
License-Expression: BSD-3-Clause
Project-URL: Homepage, https://tracklr.com
Project-URL: Download, https://gitlab.com/markuz/tracklr/-/archive/master/tracklr-master.tar.bz2
Classifier: Development Status :: 5 - Production/Stable
Classifier: Programming Language :: Python
Classifier: Programming Language :: Python :: 3
Classifier: Programming Language :: Python :: 3.11
Classifier: Programming Language :: Python :: 3.12
Classifier: Programming Language :: Python :: 3.13
Classifier: Intended Audience :: Other Audience
Classifier: Operating System :: OS Independent
Classifier: Environment :: Console
Requires-Python: >=3.9
License-File: LICENSE
Requires-Dist: appdirs
Requires-Dist: caldav
Requires-Dist: cliff
Requires-Dist: icalendar
Requires-Dist: jinja2
Requires-Dist: pyyaml>5
Requires-Dist: requests
Requires-Dist: xhtml2pdf
Provides-Extra: development
Requires-Dist: black; extra == "development"
Requires-Dist: bpython; extra == "development"
Requires-Dist: django; extra == "development"
Requires-Dist: djangorestframework; extra == "development"
Requires-Dist: drf_yasg; extra == "development"
Requires-Dist: flake8; extra == "development"
Requires-Dist: furo; extra == "development"
Requires-Dist: pip; extra == "development"
Requires-Dist: pylama; extra == "development"
Requires-Dist: pytest; extra == "development"
Requires-Dist: pytest-cov; extra == "development"
Requires-Dist: setuptools; extra == "development"
Requires-Dist: sphinx; extra == "development"
Requires-Dist: twine; extra == "development"
Requires-Dist: wheel; extra == "development"
Provides-Extra: productivity
Requires-Dist: khal; extra == "productivity"
Requires-Dist: khard; extra == "productivity"
Requires-Dist: pyfiglet; extra == "productivity"
Requires-Dist: vdirsyncer; extra == "productivity"
Dynamic: license-file
